{
    "name": "holistic",
    "description": "Holistic app platform: A system of runtime libraries, tools, and developer process for building Node.js services and stateful HTML5 applications with React and re-usable, testable, composable, remixable plug-and-play software models.",
    "version": "0.1.00",
    "codename": "alertbay",
    "author": "Encapsule",
    "copyright": {
        "holder": "Christopher D. Russell",
        "year": 2020
    },
    "contributors": [
        {
            "name": "Christopher D. Russell",
            "email": "cdr@encapsule.io",
            "url": "https://github.com/ChrisRus"
        }
    ],
    "license": "MIT",
    "buildID": "mVhDQKVTSHC3nr22pSTJtA",
    "buildSource": "bf4b2fca8f90b8c548065598fafd6cb276b2a331",
    "buildTime": 1582596017,
    "buildDateISO": "2020-02-25T02:00:17.000Z"
}
