{
    "name": "holistic",
    "description": "@encapsule/holistic is a domain engineering toolkit for building distributed applications and interactive UX from reusable software models.",
    "version": "0.2.2",
    "codename": "firestorm",
    "author": "Encapsule",
    "copyright": {
        "holder": "Chris Russell",
        "year": 2021
    },
    "contributors": [
        {
            "name": "Chris Russell",
            "email": "cdr@encapsule.io",
            "url": "https://github.com/ChrisRus"
        }
    ],
    "license": "MIT",
    "buildID": "AniKEONcQ9OPq_IkFlZVhg",
    "buildSource": "e5f49d712bbd00bf82f109f49008be6a28840905",
    "buildTime": 1637083561,
    "buildDateISO": "2021-11-16T17:26:01.000Z"
}
