{
    "name": "holistic",
    "description": "A platform for building distributed software systems with reusable JavaScript CellModel plug-ins. And, System-in-Cloud (SiC) information circuit architecture.",
    "version": "0.0.58",
    "codename": "redcoral",
    "author": "Encapsule",
    "copyright": {
        "holder": "Christopher D. Russell",
        "year": 2021
    },
    "contributors": [
        {
            "name": "Christopher D. Russell",
            "email": "cdr@encapsule.io",
            "url": "https://github.com/ChrisRus"
        }
    ],
    "license": "MIT",
    "buildID": "1KWyFu0CQzKi44OtjVEeyw",
    "buildSource": "b0d71f4514df0b61a8f4d2a5e26315974e81a528",
    "buildTime": 1615119402,
    "buildDateISO": "2021-03-07T12:16:42.000Z"
}
