{
    "name": "holistic",
    "description": "A domain and process modeling system for building Node.js/HTML5 SaaS and PaaS products dynamically from JSON data + remixable plug-ins written in JavaScript.",
    "version": "0.0.51",
    "codename": "ametrine",
    "author": "Encapsule",
    "copyright": {
        "holder": "Christopher D. Russell",
        "year": 2021
    },
    "contributors": [
        {
            "name": "Christopher D. Russell",
            "email": "cdr@encapsule.io",
            "url": "https://github.com/ChrisRus"
        }
    ],
    "license": "MIT",
    "buildID": "teLkmXGGQJO57YJyL_o88w",
    "buildSource": "20cd74bb47a0c82310105a36c2207d7c596c844f",
    "buildTime": 1613581480,
    "buildDateISO": "2021-02-17T17:04:40.000Z"
}
